tornado_webhook/__about__.py
tornado_webhook/__init__.py
tornado_webhook/__main__.py
tornado_webhook-0.2.0.dist-info/METADATA
tornado_webhook-0.2.0.dist-info/WHEEL
tornado_webhook-0.2.0.dist-info/entry_points.txt
tornado_webhook-0.2.0.dist-info/license_files/LICENSE.txt
tornado_webhook-0.2.0.dist-info/RECORD
