Metadata-Version: 2.1
Name: tornado-webhook
Version: 0.2.0
Summary: Tornado Webhook is a web application to execute webhook actions.
Project-URL: Documentation, https://github.com/hanwentao/tornado-webhook#readme
Project-URL: Issues, https://github.com/hanwentao/tornado-webhook/issues
Project-URL: Source, https://github.com/hanwentao/tornado-webhook
Author-email: Wentao Han <wentao.han@gmail.com>
Keywords: tornado,webhook
Classifier: Development Status :: 4 - Beta
Classifier: Programming Language :: Python
Classifier: Programming Language :: Python :: 3.10
Classifier: Programming Language :: Python :: 3.7
Classifier: Programming Language :: Python :: 3.8
Classifier: Programming Language :: Python :: 3.9
Classifier: Programming Language :: Python :: Implementation :: CPython
Classifier: Programming Language :: Python :: Implementation :: PyPy
Requires-Python: >=3.7
Requires-Dist: pyyaml
Requires-Dist: tornado
